README.md
setup.cfg
setup.py
reimportlib/__init__.py
reimportlib.egg-info/PKG-INFO
reimportlib.egg-info/SOURCES.txt
reimportlib.egg-info/dependency_links.txt
reimportlib.egg-info/top_level.txt
reimportlib.egg-info/zip-safe