Metadata-Version: 2.1
Name: reimportlib
Version: 1.0.2
Summary: reimportlib: refactored imports
Home-page: https://github.com/guilt/reimportlib
Author: Karthik Kumar Viswanathan
Author-email: karthikkumar@gmail.com
License: BSD
Keywords: importlib refactor module rename move serialize
Platform: UNKNOWN
Classifier: Topic :: Software Development :: Libraries :: Python Modules
